<?xml version="1.0" encoding="utf-8"?>
<jpad_config>
    <aircraft id="DASH-8" type="TURBOPROP" regulations="FAR_25">
		<global_data>
			<cabin_configuration file="cabin_configuration_DASH8.xml"> </cabin_configuration>
		</global_data>
        <lifting_surfaces>
            <wing file="wing_DASH8.xml">
                <position>
                    <x unit="m">13.73</x>
                    <y unit="m">0.0</y>
                    <z unit="m">0.95</z>
                </position>
                <rigging_angle unit="deg">0.55</rigging_angle>
            </wing>
            <horizontal_tail file="htail_DASH8.xml">
                <position>
                    <x unit="m">30.14</x>
                    <y unit="m">0.0</y>
                    <z unit="m">5.45</z>
                </position>
                <rigging_angle unit="deg">0.0</rigging_angle>
            </horizontal_tail>
            <vertical_tail file="vtail_DASH8.xml">
                <position>
                    <x unit="m">26.71</x>
                    <y unit="m">0.0</y>
                    <z unit="m">1.28</z>
                </position>
                <rigging_angle unit="deg">0.0</rigging_angle>
            </vertical_tail>
        </lifting_surfaces>
        <fuselages>
            <fuselage file="fuselage_DASH8.xml">
                <position>
                    <x unit="m">0.0</x>
                    <y unit="m">0.0</y>
                    <z unit="m">0.0</z>
                </position>
            </fuselage>
        </fuselages>
		<power_plant>
            <engine file="engine_DASH8.xml">
                <position>
                    <x unit="m">10.52</x>
                    <y unit="m">4.26</y>
                    <z unit="m">0.87</z>
                </position>
                <tilting_angle unit="deg">0.0</tilting_angle>
				<mounting_point>WING</mounting_point>
            </engine>
            <engine file="engine_DASH8.xml">
                <position>
                    <x unit="m">10.52</x>
                    <y unit="m">-4.26</y>
                    <z unit="m">0.87</z>
                </position>
                <tilting_angle unit="deg">0.0</tilting_angle>
                <mounting_point>WING</mounting_point>
            </engine>
		</power_plant> 
		<nacelles>
            <nacelle file="nacelle_DASH8.xml">
                <position>
                    <x unit="m">11.7</x>
                    <y unit="m">4.26</y>
                    <z unit="m">0.87</z>
                </position>
                <mounting_point>WING</mounting_point>
            </nacelle>
            <nacelle file="nacelle_DASH8.xml">
                <position>
                    <x unit="m">11.7</x>
                    <y unit="m">-4.26</y>
                    <z unit="m">0.87</z>
                </position>
                <mounting_point>WING</mounting_point>
            </nacelle>
		</nacelles> 
		<landing_gears file="landing_gear_DASH8.xml">
			<position>
                <x unit="m">15.4</x>
                <y unit="m">0.0</y>
                <z unit="m">-0.34</z>
            </position>
			<mounting_point>NACELLE</mounting_point>
		</landing_gears>
		<systems file="systems_DASH8.xml">
			<position>
                <x unit="m">0.0</x>
                <y unit="m">0.0</y>
                <z unit="m">0.0</z>
            </position>
		</systems>
    </aircraft>
</jpad_config>