<database.databasefunctions.FuelFractionDatabaseReader>
  <databaseFolderPath>D:\JPAD\jpad\JPADSandBox_v2\data\</databaseFolderPath>
  <databaseFileName>FuelFractions.h5</databaseFileName>
  <database>
    <__fileName>D:\JPAD\jpad\JPADSandBox_v2\data\FuelFractions.h5</__fileName>
    <__fileH5 serialization="custom">
      <file>
        <default>
          <path>D:\JPAD\jpad\JPADSandBox_v2\data\FuelFractions.h5</path>
        </default>
        <char>\</char>
      </file>
      <ncsa.hdf.object.FileFormat>
        <default>
          <fid>16777227</fid>
          <isReadOnly>true</isReadOnly>
          <max__members>10000</max__members>
          <start__members>0</start__members>
          <fullFileName>D:\JPAD\jpad\JPADSandBox_v2\data\FuelFractions.h5</fullFileName>
        </default>
      </ncsa.hdf.object.FileFormat>
      <ncsa.hdf.object.h5.H5File>
        <default>
          <attrFlag>false</attrFlag>
          <flag>0</flag>
          <indexOrder>0</indexOrder>
          <indexType>0</indexType>
          <libver>
            <int>0</int>
            <int>0</int>
          </libver>
        </default>
      </ncsa.hdf.object.h5.H5File>
    </__fileH5>
    <__rootGroup>
      <filename>D:\JPAD\jpad\JPADSandBox_v2\data\FuelFractions.h5</filename>
      <fileFormat class="ncsa.hdf.object.h5.H5File" reference="../../__fileH5"/>
      <name>/</name>
      <fullName>/</fullName>
      <oid>
        <long>96</long>
      </oid>
      <memberList class="vector">
        <ncsa.hdf.object.h5.H5ScalarDS>
          <filename>D:\JPAD\jpad\JPADSandBox_v2\data\FuelFractions.h5</filename>
          <fileFormat class="ncsa.hdf.object.h5.H5File" reference="../../../../__fileH5"/>
          <name>FuelFractions_Roskam</name>
          <path>/</path>
          <fullName>/FuelFractions_Roskam</fullName>
          <oid>
            <long>800</long>
          </oid>
          <rank>0</rank>
          <selectedIndex>
            <int>0</int>
            <int>1</int>
            <int>2</int>
          </selectedIndex>
          <compression>NONE</compression>
          <convertByteToString>true</convertByteToString>
          <isDataLoaded>false</isDataLoaded>
          <nPoints>1</nPoints>
          <enumConverted>false</enumConverted>
          <interlace>-1</interlace>
          <isImage>false</isImage>
          <isTrueColor>false</isTrueColor>
          <isText>false</isText>
          <isUnsigned>false</isUnsigned>
          <unsignedConverted>false</unsignedConverted>
          <filteredImageValues class="vector"/>
          <isImageDisplay>false</isImageDisplay>
          <isDefaultImageOrder>true</isDefaultImageOrder>
          <isFillValueConverted>false</isFillValueConverted>
          <isVLEN>false</isVLEN>
          <isEnum>false</isEnum>
          <isExternal>false</isExternal>
          <isArrayOfCompound>false</isArrayOfCompound>
          <isArrayOfVLEN>false</isArrayOfVLEN>
          <isNativeDatatype>false</isNativeDatatype>
          <isRegRef>false</isRegRef>
          <nAttributes>-1</nAttributes>
          <obj__info>
            <fileno>-1</fileno>
            <addr>-1</addr>
            <type>0</type>
            <rc>0</rc>
            <atime>0</atime>
            <mtime>0</mtime>
            <ctime>0</ctime>
            <btime>0</btime>
            <num__attrs>-1</num__attrs>
          </obj__info>
        </ncsa.hdf.object.h5.H5ScalarDS>
        <ncsa.hdf.object.h5.H5ScalarDS>
          <filename>D:\JPAD\jpad\JPADSandBox_v2\data\FuelFractions.h5</filename>
          <fileFormat class="ncsa.hdf.object.h5.H5File" reference="../../../../__fileH5"/>
          <name>RoskamFuelFraction.PNG</name>
          <path>/</path>
          <fullName>/RoskamFuelFraction.PNG</fullName>
          <oid>
            <long>891980</long>
          </oid>
          <rank>0</rank>
          <selectedIndex>
            <int>0</int>
            <int>1</int>
            <int>2</int>
          </selectedIndex>
          <compression>NONE</compression>
          <convertByteToString>true</convertByteToString>
          <isDataLoaded>false</isDataLoaded>
          <nPoints>1</nPoints>
          <enumConverted>false</enumConverted>
          <interlace>-1</interlace>
          <isImage>false</isImage>
          <isTrueColor>false</isTrueColor>
          <isText>false</isText>
          <isUnsigned>false</isUnsigned>
          <unsignedConverted>false</unsignedConverted>
          <filteredImageValues class="vector"/>
          <isImageDisplay>false</isImageDisplay>
          <isDefaultImageOrder>true</isDefaultImageOrder>
          <isFillValueConverted>false</isFillValueConverted>
          <isVLEN>false</isVLEN>
          <isEnum>false</isEnum>
          <isExternal>false</isExternal>
          <isArrayOfCompound>false</isArrayOfCompound>
          <isArrayOfVLEN>false</isArrayOfVLEN>
          <isNativeDatatype>false</isNativeDatatype>
          <isRegRef>false</isRegRef>
          <nAttributes>-1</nAttributes>
          <obj__info>
            <fileno>-1</fileno>
            <addr>-1</addr>
            <type>0</type>
            <rc>0</rc>
            <atime>0</atime>
            <mtime>0</mtime>
            <ctime>0</ctime>
            <btime>0</btime>
            <num__attrs>-1</num__attrs>
          </obj__info>
        </ncsa.hdf.object.h5.H5ScalarDS>
      </memberList>
      <nMembersInFile>2</nMembersInFile>
      <nAttributes>-1</nAttributes>
      <obj__info>
        <fileno>-1</fileno>
        <addr>-1</addr>
        <type>0</type>
        <rc>0</rc>
        <atime>0</atime>
        <mtime>0</mtime>
        <ctime>0</ctime>
        <btime>0</btime>
        <num__attrs>-1</num__attrs>
      </obj__info>
    </__rootGroup>
  </database>
</database.databasefunctions.FuelFractionDatabaseReader>